rtl/neosd_dat_crc.sv
module neosd_dat_crc (
    input clk_i,
    input rstn_i,
    // Strobe to obtain the slow SD clock
    input clkstrb_i,

    input data_s_i,
    input shift_s_i,
    input output_s_i,
    output data_s_o,
    output nonzero_o
);
    logic[15:0] sreg;
    logic sreg_fb;

    assign nonzero_o = |sreg;
    assign data_s_o = sreg[0];
    // If we're shifting out, sreg_fb should be 0 so that we don't modify stored values
    assign sreg_fb = (data_s_i ^ sreg[0]) & ~output_s_i;

    always @(posedge clk_i or negedge rstn_i) begin
        if (rstn_i == 1'b0) begin
            sreg <= '0;
        end else begin
            if (clkstrb_i == 1'b1 && shift_s_i == 1'b1) begin
                sreg[15] <= sreg_fb;
                sreg[14:11] <= sreg[15:12];
                sreg[10] <= sreg[11] ^ sreg_fb;
                sreg[9:4] <= sreg[10:5];
                sreg[3] <= sreg[4] ^ sreg_fb;
                sreg[2:0] <= sreg[3:1];
            end
        end
    end
endmodule

rtl/neosd_dat_reg.sv
module neosd_dat_reg (
    input clk_i,
    // Strobe to obtain the slow SD clock
    input clkstrb_i,
    input rstn_i,

    input[7:0] data_p_i,
    input load_p_i,
    output reg[7:0] data_p_o,

    input data_s_i,
    input shift_s_i,
    output data_s_o
);

    always @(posedge clk_i or negedge rstn_i) begin
        if (rstn_i == 1'b0) begin
            data_p_o <= '0;
        end else begin
            // Load using fast clock
            if (load_p_i != 1'b0) begin
                data_p_o[7:0] <= data_p_i[31:0];
            // Shift using slow clock
            end else if (clkstrb_i == 1'b1 && shift_s_i == 1'b1) begin
                data_p_o <= {data_p_o[6:0], data_s_i};
            end
        end
    end

    assign data_s_o = data_p_o[7];

endmodule

rtl/neosd_dat_block.sv
module neosd_dat_block (
    input clk_i,
    // Strobe to obtain the slow SD clock
    input clkstrb_i,
    input rstn_i,

    // Control signals:
    // Read or write mode
    input ctrl_rnw_i,
    // 4 wire mode
    input ctrl_d4_i,
    // Rotate the registers in 1 bit mode, so input / output is muxed to different regs
    input ctrl_rot_reg,
    // Output '0' (0), '1' (1), register data (2) or crc (3). Independent of shift_s_i
    input[1:0] ctrl_omux_i,
    // Make CRC generators output CRC
    input ctrl_output_crc_i,

    input sd_dat0_i,
    input sd_dat1_i,
    input sd_dat2_i,
    input sd_dat3_i,

    output sd_dat0_o,
    output sd_dat1_o,
    output sd_dat2_o,
    output sd_dat3_o,

    // Enable the shift registers
    input shift_s_i,
    output crc_nonzero_o,

    // Data register
    input[31:0] data_p_i,
    input load_p_i,
    output[31:0] data_p_o
);

    // For read mode: The input, either 4 pin or 1 pin
    logic[3:0] reg_data_s_i;
    assign reg_data_s_i[0] = sd_dat0_i;
    assign reg_data_s_i[1] = ctrl_d4_i ? sd_dat1_i : sd_dat0_i;
    assign reg_data_s_i[2] = ctrl_d4_i ? sd_dat2_i : sd_dat0_i;
    assign reg_data_s_i[3] = ctrl_d4_i ? sd_dat3_i : sd_dat0_i;

    // CRC input muxes
    logic[3:0] crc_data_s_i;
    assign crc_data_s_i[0] = ctrl_rnw_i ? reg_data_s_i[0] : sd_dat0_o;
    assign crc_data_s_i[1] = ctrl_rnw_i ? reg_data_s_i[1] : sd_dat1_o;
    assign crc_data_s_i[2] = ctrl_rnw_i ? reg_data_s_i[2] : sd_dat2_o;
    assign crc_data_s_i[3] = ctrl_rnw_i ? reg_data_s_i[3] : sd_dat3_o;

    // In read mode: if 1 pin mode, reg should read only read every 4th element
    logic[1:0] reg_active_n;
    always @(posedge clk_i or negedge rstn_i) begin
        if (rstn_i == 1'b0) begin
            reg_active_n <= '0;
        end else begin
            if (clkstrb_i == 1'b1 && shift_s_i == 1'b1 && ctrl_rot_reg == 1'b1) begin
                reg_active_n <= reg_active_n + 1;
            end
        end
    end
    // In read mode: Gate the shift enable accordingly
    logic[3:0] reg_shift_s_i;
    assign reg_shift_s_i[0] = shift_s_i && ((reg_active_n == 0) || ctrl_d4_i);
    assign reg_shift_s_i[1] = shift_s_i && ((reg_active_n == 1) || ctrl_d4_i);
    assign reg_shift_s_i[2] = shift_s_i && ((reg_active_n == 2) || ctrl_d4_i);
    assign reg_shift_s_i[3] = shift_s_i && ((reg_active_n == 3) || ctrl_d4_i);

    // CRC result in read: In D4 mode, check all CRCs
    // In D0, all CRCs get the same data, so can or as well
    logic[3:0] crc_nonzero;
    assign crc_nonzero_o = |crc_nonzero;

    logic[7:0] reg_data_p_i[3:0];
    logic[7:0] reg_data_p_o[3:0];
    logic[3:0] reg_data_s_o, mux_data_s_o, crc_data_s_o;

    genvar i, j;
    generate
        for (i = 0; i < 4; i = i + 1) begin: regs
            neosd_dat_reg regi (
                .clk_i(clk_i),
                .clkstrb_i(clkstrb_i),
                .rstn_i(rstn_i),
                .data_p_i(reg_data_p_i[i]),
                .load_p_i(load_p_i),
                .data_p_o(reg_data_p_o[i]),
                .data_s_i(reg_data_s_i[i]),
                .shift_s_i(reg_shift_s_i[i]),
                .data_s_o(reg_data_s_o[i])
            );
            neosd_dat_crc crci (
                .clk_i(clk_i),
                .clkstrb_i(clkstrb_i),
                .rstn_i(rstn_i),
                .data_s_i(crc_data_s_i[i]),
                .shift_s_i(shift_s_i),
                .output_s_i(ctrl_output_crc_i),
                .data_s_o(crc_data_s_o[i]),
                .nonzero_o(crc_nonzero[i])
            );

            // Properly assign the reg_data_p_i/o for all registers
            for (j = 0; j < 8; j++) begin
                    assign reg_data_p_i[i][j] = data_p_i[j*4 + i];
                    assign data_p_o[j*4 + i] = reg_data_p_o[i][j];
            end

            // Output multiplexers
            assign mux_data_s_o[i] = (ctrl_omux_i == 2'b00) ? 1'b0 :
                                     (ctrl_omux_i == 2'b01) ? 1'b1 :
                                     (ctrl_omux_i == 2'b10) ? reg_data_s_o[i] :
                                     crc_data_s_o[i];
        end
    endgenerate

    // Drive outputs from muxes. dat0 in D0 mode muxes from all regs
    assign sd_dat0_o = mux_data_s_o[reg_active_n & {2{!ctrl_d4_i}}];
    assign sd_dat1_o = mux_data_s_o[1];
    assign sd_dat2_o = mux_data_s_o[2];
    assign sd_dat3_o = mux_data_s_o[3];

endmodule

test/tb_dat_block.v
`default_nettype none
`timescale 1ns / 1ps

module tb_dat_block ();

    initial begin
        $dumpfile("tb_data_block.vcd");
        $dumpvars(0, tb_dat_block);
        #1;
    end

    wire clk_i;
    wire clkstrb_i;
    wire rstn_i;
  
    wire ctrl_rnw_i;
    wire ctrl_d4_i;
    wire ctrl_rot_reg;
    wire [1:0] ctrl_omux_i;
    wire ctrl_output_crc_i;
  
    wire sd_dat0_i;
    wire sd_dat1_i;
    wire sd_dat2_i;
    wire sd_dat3_i;
  
    wire sd_dat0_o;
    wire sd_dat1_o;
    wire sd_dat2_o;
    wire sd_dat3_o;

    wire sd_dat_oe;
    assign sd_dat_oe = 0;
  
    wire shift_s_i;
    wire crc_nonzero_o;
    wire [31:0] data_p_i;
    wire load_p_i;
    wire [31:0] data_p_o;
  
    neosd_dat_block u_neosd_dat_block (
      .clk_i(clk_i),
      .clkstrb_i(clkstrb_i),
      .rstn_i(rstn_i),

      .ctrl_rnw_i(ctrl_rnw_i),
      .ctrl_d4_i(ctrl_d4_i),
      .ctrl_rot_reg(ctrl_rot_reg),
      .ctrl_omux_i(ctrl_omux_i),
      .ctrl_output_crc_i(ctrl_output_crc_i),

      .sd_dat0_i(sd_dat0_i),
      .sd_dat1_i(sd_dat1_i),
      .sd_dat2_i(sd_dat2_i),
      .sd_dat3_i(sd_dat3_i),
      .sd_dat0_o(sd_dat0_o),
      .sd_dat1_o(sd_dat1_o),
      .sd_dat2_o(sd_dat2_o),
      .sd_dat3_o(sd_dat3_o),

      .shift_s_i(shift_s_i),
      .crc_nonzero_o(crc_nonzero_o),
      .data_p_i(data_p_i),
      .load_p_i(load_p_i),
      .data_p_o(data_p_o)
    );

endmodule

test/tb_data_block.vcd
$date
	Sat Aug  2 16:55:23 2025
$end
$version
	Icarus Verilog
$end
$timescale
	1ps
$end
$scope module tb_dat_block $end
$var wire 1 ! clk_i $end
$var wire 1 " clkstrb_i $end
$var wire 1 # ctrl_d4_i $end
$var wire 2 $ ctrl_omux_i [1:0] $end
$var wire 1 % ctrl_output_crc_i $end
$var wire 1 & ctrl_rnw_i $end
$var wire 1 ' ctrl_rot_reg $end
$var wire 32 ( data_p_i [31:0] $end
$var wire 1 ) load_p_i $end
$var wire 1 * rstn_i $end
$var wire 1 + sd_dat0_i $end
$var wire 1 , sd_dat1_i $end
$var wire 1 - sd_dat2_i $end
$var wire 1 . sd_dat3_i $end
$var wire 1 / sd_dat_oe $end
$var wire 1 0 shift_s_i $end
$var wire 1 1 sd_dat3_o $end
$var wire 1 2 sd_dat2_o $end
$var wire 1 3 sd_dat1_o $end
$var wire 1 4 sd_dat0_o $end
$var wire 32 5 data_p_o [31:0] $end
$var wire 1 6 crc_nonzero_o $end
$scope module u_neosd_dat_block $end
$var wire 1 ! clk_i $end
$var wire 1 " clkstrb_i $end
$var wire 1 # ctrl_d4_i $end
$var wire 2 7 ctrl_omux_i [1:0] $end
$var wire 1 % ctrl_output_crc_i $end
$var wire 1 & ctrl_rnw_i $end
$var wire 1 ' ctrl_rot_reg $end
$var wire 32 8 data_p_i [31:0] $end
$var wire 1 ) load_p_i $end
$var wire 1 * rstn_i $end
$var wire 1 + sd_dat0_i $end
$var wire 1 , sd_dat1_i $end
$var wire 1 - sd_dat2_i $end
$var wire 1 . sd_dat3_i $end
$var wire 1 0 shift_s_i $end
$var wire 1 1 sd_dat3_o $end
$var wire 1 2 sd_dat2_o $end
$var wire 1 3 sd_dat1_o $end
$var wire 1 4 sd_dat0_o $end
$var wire 4 9 reg_shift_s_i [3:0] $end
$var wire 4 : reg_data_s_o [3:0] $end
$var wire 4 ; reg_data_s_i [3:0] $end
$var wire 4 < mux_data_s_o [3:0] $end
$var wire 32 = data_p_o [31:0] $end
$var wire 1 6 crc_nonzero_o $end
$var wire 4 > crc_nonzero [3:0] $end
$var wire 4 ? crc_data_s_o [3:0] $end
$var wire 4 @ crc_data_s_i [3:0] $end
$var reg 2 A reg_active_n [1:0] $end
$scope begin regs[0] $end
$var parameter 2 B i $end
$scope begin genblk1[0] $end
$var parameter 2 C j $end
$upscope $end
$scope begin genblk1[1] $end
$var parameter 2 D j $end
$upscope $end
$scope begin genblk1[2] $end
$var parameter 3 E j $end
$upscope $end
$scope begin genblk1[3] $end
$var parameter 3 F j $end
$upscope $end
$scope begin genblk1[4] $end
$var parameter 4 G j $end
$upscope $end
$scope begin genblk1[5] $end
$var parameter 4 H j $end
$upscope $end
$scope begin genblk1[6] $end
$var parameter 4 I j $end
$upscope $end
$scope begin genblk1[7] $end
$var parameter 4 J j $end
$upscope $end
$scope module crci $end
$var wire 1 ! clk_i $end
$var wire 1 " clkstrb_i $end
$var wire 1 K data_s_i $end
$var wire 1 % output_s_i $end
$var wire 1 * rstn_i $end
$var wire 1 0 shift_s_i $end
$var wire 1 L sreg_fb $end
$var wire 1 M nonzero_o $end
$var wire 1 N data_s_o $end
$var reg 16 O sreg [15:0] $end
$upscope $end
$scope module regi $end
$var wire 1 ! clk_i $end
$var wire 1 " clkstrb_i $end
$var wire 8 P data_p_i [7:0] $end
$var wire 1 Q data_s_i $end
$var wire 1 ) load_p_i $end
$var wire 1 * rstn_i $end
$var wire 1 R shift_s_i $end
$var wire 1 S data_s_o $end
$var reg 8 T data_p_o [7:0] $end
$upscope $end
$upscope $end
$scope begin regs[1] $end
$var parameter 2 U i $end
$scope begin genblk1[0] $end
$var parameter 2 V j $end
$upscope $end
$scope begin genblk1[1] $end
$var parameter 2 W j $end
$upscope $end
$scope begin genblk1[2] $end
$var parameter 3 X j $end
$upscope $end
$scope begin genblk1[3] $end
$var parameter 3 Y j $end
$upscope $end
$scope begin genblk1[4] $end
$var parameter 4 Z j $end
$upscope $end
$scope begin genblk1[5] $end
$var parameter 4 [ j $end
$upscope $end
$scope begin genblk1[6] $end
$var parameter 4 \ j $end
$upscope $end
$scope begin genblk1[7] $end
$var parameter 4 ] j $end
$upscope $end
$scope module crci $end
$var wire 1 ! clk_i $end
$var wire 1 " clkstrb_i $end
$var wire 1 ^ data_s_i $end
$var wire 1 % output_s_i $end
$var wire 1 * rstn_i $end
$var wire 1 0 shift_s_i $end
$var wire 1 _ sreg_fb $end
$var wire 1 ` nonzero_o $end
$var wire 1 a data_s_o $end
$var reg 16 b sreg [15:0] $end
$upscope $end
$scope module regi $end
$var wire 1 ! clk_i $end
$var wire 1 " clkstrb_i $end
$var wire 8 c data_p_i [7:0] $end
$var wire 1 d data_s_i $end
$var wire 1 ) load_p_i $end
$var wire 1 * rstn_i $end
$var wire 1 e shift_s_i $end
$var wire 1 f data_s_o $end
$var reg 8 g data_p_o [7:0] $end
$upscope $end
$upscope $end
$scope begin regs[2] $end
$var parameter 3 h i $end
$scope begin genblk1[0] $end
$var parameter 2 i j $end
$upscope $end
$scope begin genblk1[1] $end
$var parameter 2 j j $end
$upscope $end
$scope begin genblk1[2] $end
$var parameter 3 k j $end
$upscope $end
$scope begin genblk1[3] $end
$var parameter 3 l j $end
$upscope $end
$scope begin genblk1[4] $end
$var parameter 4 m j $end
$upscope $end
$scope begin genblk1[5] $end
$var parameter 4 n j $end
$upscope $end
$scope begin genblk1[6] $end
$var parameter 4 o j $end
$upscope $end
$scope begin genblk1[7] $end
$var parameter 4 p j $end
$upscope $end
$scope module crci $end
$var wire 1 ! clk_i $end
$var wire 1 " clkstrb_i $end
$var wire 1 q data_s_i $end
$var wire 1 % output_s_i $end
$var wire 1 * rstn_i $end
$var wire 1 0 shift_s_i $end
$var wire 1 r sreg_fb $end
$var wire 1 s nonzero_o $end
$var wire 1 t data_s_o $end
$var reg 16 u sreg [15:0] $end
$upscope $end
$scope module regi $end
$var wire 1 ! clk_i $end
$var wire 1 " clkstrb_i $end
$var wire 8 v data_p_i [7:0] $end
$var wire 1 w data_s_i $end
$var wire 1 ) load_p_i $end
$var wire 1 * rstn_i $end
$var wire 1 x shift_s_i $end
$var wire 1 y data_s_o $end
$var reg 8 z data_p_o [7:0] $end
$upscope $end
$upscope $end
$scope begin regs[3] $end
$var parameter 3 { i $end
$scope begin genblk1[0] $end
$var parameter 2 | j $end
$upscope $end
$scope begin genblk1[1] $end
$var parameter 2 } j $end
$upscope $end
$scope begin genblk1[2] $end
$var parameter 3 ~ j $end
$upscope $end
$scope begin genblk1[3] $end
$var parameter 3 !" j $end
$upscope $end
$scope begin genblk1[4] $end
$var parameter 4 "" j $end
$upscope $end
$scope begin genblk1[5] $end
$var parameter 4 #" j $end
$upscope $end
$scope begin genblk1[6] $end
$var parameter 4 $" j $end
$upscope $end
$scope begin genblk1[7] $end
$var parameter 4 %" j $end
$upscope $end
$scope module crci $end
$var wire 1 ! clk_i $end
$var wire 1 " clkstrb_i $end
$var wire 1 &" data_s_i $end
$var wire 1 % output_s_i $end
$var wire 1 * rstn_i $end
$var wire 1 0 shift_s_i $end
$var wire 1 '" sreg_fb $end
$var wire 1 (" nonzero_o $end
$var wire 1 )" data_s_o $end
$var reg 16 *" sreg [15:0] $end
$upscope $end
$scope module regi $end
$var wire 1 ! clk_i $end
$var wire 1 " clkstrb_i $end
$var wire 8 +" data_p_i [7:0] $end
$var wire 1 ," data_s_i $end
$var wire 1 ) load_p_i $end
$var wire 1 * rstn_i $end
$var wire 1 -" shift_s_i $end
$var wire 1 ." data_s_o $end
$var reg 8 /" data_p_o [7:0] $end
$upscope $end
$upscope $end
$upscope $end
$upscope $end
$enddefinitions $end
$comment Show the parameter values. $end
$dumpall
b111 %"
b110 $"
b101 #"
b100 ""
b11 !"
b10 ~
b1 }
b0 |
b11 {
b111 p
b110 o
b101 n
b100 m
b11 l
b10 k
b1 j
b0 i
b10 h
b111 ]
b110 \
b101 [
b100 Z
b11 Y
b10 X
b1 W
b0 V
b1 U
b111 J
b110 I
b101 H
b100 G
b11 F
b10 E
b1 D
b0 C
b0 B
$end
#0
$dumpvars
b0 /"
0."
x-"
z,"
bz +"
b0 *"
0)"
0("
x'"
x&"
b0 z
0y
xx
zw
bz v
b0 u
0t
0s
xr
xq
b0 g
0f
xe
zd
bz c
b0 b
0a
0`
x_
x^
b0 T
0S
xR
zQ
bz P
b0 O
0N
0M
xL
xK
b0 A
bx @
b0 ?
b0 >
b0 =
bx <
bz ;
b0 :
bx 9
bz 8
bz 7
06
b0 5
x4
x3
x2
x1
z0
0/
z.
z-
z,
z+
0*
z)
bz (
z'
z&
z%
bz $
z#
z"
1!
$end
#5000
0!
#10000
1!
#15000
0!
#20000
1'"
1r
1_
1L
1&"
1q
1^
1K
b1111 @
b11110001 P
b11110010 c
b11110100 v
b11111000 +"
0-"
0x
0e
0R
13
12
11
b0 9
14
b1111 <
1)
b11111111111111111000010000100001 (
b11111111111111111000010000100001 8
0"
00
0%
b1 $
b1 7
0'
1#
0&
1*
1!
#25000
0!
#30000
b11111111111111111000010000100001 5
b11111111111111111000010000100001 =
b1111 :
1."
1y
1f
1S
b11111000 /"
b11110100 z
b11110010 g
b11110001 T
1!
#35000
0!
#40000
1!
#45000
0!
#50000
1"
1!
#55000
0!
#60000
0'"
0r
0_
0L
0&"
0q
0^
0K
b0 @
03
02
01
b0 P
b0 c
b0 v
b0 +"
04
b0 <
b0 $
b0 7
1/
0)
b0 (
b0 8
0"
1!
#65000
0!
#70000
1!
#75000
0!
#80000
1!
#85000
0!
#90000
1"
1!
#95000
0!
#100000
1'"
1r
1_
1L
1&"
1q
1^
1K
b1111 @
13
12
11
14
b1111 <
1-"
1x
1e
1R
b1111 9
10
b10 $
b10 7
0"
1!
#105000
0!
#110000
1!
#115000
0!
#120000
1!
#125000
0!
#130000
1"
1!
#135000
0!
#140000
0"
b1111111111111000010000100001zzzz 5
b1111111111111000010000100001zzzz =
16
b1111 >
b1110001z T
1M
b1000010000001000 O
b1110010z g
1`
b1000010000001000 b
b1110100z z
1s
b1000010000001000 u
b1111000z /"
1("
b1000010000001000 *"
1!
#145000
0!
#150000
1!
#155000
0!
#160000
1!
#165000
0!
#170000
1"
1!
#175000
0!
#180000
0"
b111111111000010000100001zzzzzzzz 5
b111111111000010000100001zzzzzzzz =
b110001zz T
b1100011000001100 O
b110010zz g
b1100011000001100 b
b110100zz z
b1100011000001100 u
b111000zz /"
b1100011000001100 *"
1!
#185000
0!
#190000
1!
#195000
0!
#200000
1!
#205000
0!
#210000
1"
1!
#215000
0!
#220000
0"
b11111000010000100001zzzzzzzzzzzz 5
b11111000010000100001zzzzzzzzzzzz =
b10001zzz T
b1110011100001110 O
b10010zzz g
b1110011100001110 b
b10100zzz z
b1110011100001110 u
b11000zzz /"
b1110011100001110 *"
1!
#225000
0!
#230000
1!
#235000
0!
#240000
1!
#245000
0!
#250000
1"
1!
#255000
0!
#260000
0"
0q
0^
0K
b1000 @
03
02
04
b1000 <
b1000010000100001zzzzzzzzzzzzzzzz 5
b1000010000100001zzzzzzzzzzzzzzzz =
1L
1_
1r
0'"
b1000 :
b1111 ?
0S
1N
0f
1a
0y
1t
1)"
b1zzzz T
b1111011110001111 O
b10zzzz g
b1111011110001111 b
b100zzzz z
b1111011110001111 u
b1000zzzz /"
b1111011110001111 *"
1!
#265000
0!
#270000
1!
#275000
0!
#280000
1!
#285000
0!
#290000
1"
1!
#295000
0!
#300000
0"
1'"
0r
0&"
1q
b100 @
12
01
b100 <
b10000100001zzzzzzzzzzzzzzzzzzzz 5
b10000100001zzzzzzzzzzzzzzzzzzzz =
b100 :
1y
0."
b1zzzzz T
b1111111111001111 O
b10zzzzz g
b1111111111001111 b
b100zzzzz z
b1111111111001111 u
b0zzzzz /"
b111101111000111 *"
1!
#305000
0!
#310000
1!
#315000
0!
#320000
1!
#325000
0!
#330000
1"
1!
#335000
0!
#340000
0"
1r
0_
0q
1^
b10 @
13
02
b10 <
b100001zzzzzzzzzzzzzzzzzzzzzzzz 5
b100001zzzzzzzzzzzzzzzzzzzzzzzz =
b10 :
1f
0y
b1zzzzzz T
b1111101111101111 O
b10zzzzzz g
b1111101111101111 b
b0zzzzzz z
b111111111100111 u
b0zzzzzz /"
b1011100111101011 *"
1!
#345000
0!
#350000
1!
#355000
0!
#360000
1!
#365000
0!
#370000
1"
1!
#375000
0!
#380000
0"
1_
0L
0^
1K
b1 @
03
14
b1 <
b1zzzzzzzzzzzzzzzzzzzzzzzzzzzz 5
b1zzzzzzzzzzzzzzzzzzzzzzzzzzzz =
b1 :
1S
0f
b1zzzzzzz T
b1111100111111111 O
b0zzzzzzz g
b111110111110111 b
b0zzzzzzz z
b1011101111111011 u
b0zzzzzzz /"
b1101100011111101 *"
1!
#385000
0!
#390000
1!
#395000
0!
#400000
1!
#405000
0!
#410000
1"
1!
#415000
0!
#420000
b11110001 P
b11110010 c
b11110100 v
b11111000 +"
0-"
0x
0e
0R
b0 9
1)
b11111111111111111000010000100001 (
b11111111111111111000010000100001 8
0/
00
0"
xr
x_
xL
z&"
zq
z^
zK
bz @
z3
z2
z1
z4
bz <
bz 5
bz =
x'"
bz :
b111 ?
zS
zf
zy
z."
0)"
bz T
b111110011111111 O
bz g
b1011101011110011 b
bz z
b1101100111110101 u
bz /"
b1110100001110110 *"
1!
#425000
0!
#430000
1'"
0r
0_
0L
1&"
1q
1^
1K
b1111 @
13
12
11
14
b1111 <
b11111111111111111000010000100001 5
b11111111111111111000010000100001 =
b1111 :
1."
1y
1f
1S
b11111000 /"
b11110100 z
b11110010 g
b11110001 T
1!
#435000
0!
#440000
1!
#445000
0!
#450000
1"
1!
#455000
0!
#460000
1-"
1x
1e
1R
b0 P
b0 c
b0 v
b0 +"
b1111 9
10
1/
0)
b0 (
b0 8
0"
1!
#465000
0!
#470000
1!
#475000
0!
#480000
1!
#485000
0!
#490000
1"
1!
#495000
0!
#500000
0"
b1111111111111000010000100001zzzz 5
b1111111111111000010000100001zzzz =
1r
0'"
b1011 ?
0t
1)"
b1110001z T
b11111001111111 O
b1110010z g
b101110101111001 b
b1110100z z
b110110011111010 u
b1111000z /"
b1111000000110011 *"
1!
#505000
0!
#510000
1!
#515000
0!
#520000
1!
#525000
0!
#530000
1"
1!
#535000
0!
#540000
0"
b111111111000010000100001zzzzzzzz 5
b111111111000010000100001zzzzzzzz =
1_
0r
b1101 ?
0a
1t
b110001zz T
b1111100111111 O
b110010zz g
b10111010111100 b
b110100zz z
b1011001001110101 u
b111000zz /"
b111100000011001 *"
1!
#545000
0!
#550000
1!
#555000
0!
#560000
1!
#565000
0!
#570000
1"
1!
#575000
0!
#580000
0"
b11111000010000100001zzzzzzzzzzzz 5
b11111000010000100001zzzzzzzzzzzz =
1r
1'"
b1 ?
0t
0)"
b10001zzz T
b111110011111 O
b10010zzz g
b1001001101010110 b
b10100zzz z
b101100100111010 u
b11000zzz /"
b11110000001100 *"
1!
#585000
0!
#590000
1!
#595000
0!
#600000
1!
#605000
0!
#610000
1"
1!
#615000
0!
#620000
0"
1L
0q
0^
0K
b1000 @
03
02
04
b1000 <
b1000010000100001zzzzzzzzzzzzzzzz 5
b1000010000100001zzzzzzzzzzzzzzzz =
1_
1r
b1000 :
b111 ?
0S
0f
1a
0y
1t
b1zzzz T
b11111001111 O
b10zzzz g
b1100110110100011 b
b100zzzz z
b1010100010010101 u
b1000zzzz /"
b1001101000001110 *"
1!
#625000
0!
#630000
1!
#635000
0!
#640000
1!
#645000
0!
#650000
1"
1!
#655000
0!
#660000
0"
0&"
1q
b100 @
12
01
b100 <
b10000100001zzzzzzzzzzzzzzzzzzzz 5
b10000100001zzzzzzzzzzzzzzzzzzzz =
1r
1'"
b100 :
b1011 ?
1y
0t
0."
1)"
b1zzzzz T
b1000011111101111 O
b10zzzzz g
b1110001011011001 b
b100zzzzz z
b1101000001000010 u
b0zzzzz /"
b1100100100001111 *"
1!
#665000
0!
#670000
1!
#675000
0!
#680000
1!
#685000
0!
#690000
1"
1!
#695000
0!
#700000
0"
0q
1^
b10 @
13
02
b10 <
b100001zzzzzzzzzzzzzzzzzzzzzzzz 5
b100001zzzzzzzzzzzzzzzzzzzzzzzz =
1_
1r
b10 :
b1101 ?
1f
0a
0y
1t
b1zzzzzz T
b1100011111111111 O
b10zzzzzz g
b1111010101100100 b
b0zzzzzz z
b1110110000101001 u
b0zzzzzz /"
b1110000010001111 *"
1!
#705000
0!
#710000
1!
#715000
0!
#720000
1!
#725000
0!
#730000
1"
1!
#735000
0!
#740000
0"
0_
0L
0^
1K
b1 @
03
14
b1 <
b1zzzzzzzzzzzzzzzzzzzzzzzzzzzz 5
b1zzzzzzzzzzzzzzzzzzzzzzzzzzzz =
0r
b1 :
b1001 ?
1S
0f
0t
b1zzzzzzz T
b1110011111110111 O
b0zzzzzzz g
b1111111010111010 b
b0zzzzzzz z
b1111001000011100 u
b0zzzzzzz /"
b1111010001001111 *"
1!
#745000
0!
#750000
1!
#755000
0!
#760000
1!
#765000
0!
#770000
1"
1!
#775000
0!
#780000
b11110001 P
b11110010 c
b11110100 v
b11111000 +"
0-"
0x
0e
0R
b0 9
1)
b11111111111111111000010000100001 (
b11111111111111111000010000100001 8
0/
00
0"
x'"
xr
xL
z&"
zq
z^
zK
bz @
z3
z2
z1
z4
bz <
bz 5
bz =
x_
b1011 ?
bz :
zS
zf
1a
zy
z."
bz T
b111001111111011 O
bz g
b111111101011101 b
bz z
b111100100001110 u
bz /"
b1111111000101111 *"
1!
#785000
0!
#790000
0'"
1r
0_
0L
1&"
1q
1^
1K
b1111 @
13
12
11
14
b1111 <
b11111111111111111000010000100001 5
b11111111111111111000010000100001 =
b1111 :
1."
1y
1f
1S
b11111000 /"
b11110100 z
b11110010 g
b11110001 T
1!
#795000
0!
#800000
1!
#805000
0!
#810000
1"
1!
#815000
0!
#820000
1-"
1x
1e
1R
b0 P
b0 c
b0 v
b0 +"
b1111 9
10
1/
0)
b0 (
b0 8
0"
1!
#825000
0!
#830000
1!
#835000
0!
#840000
1!
#845000
0!
#850000
1"
1!
#855000
0!
#860000
0"
b1111111111111000010000100001zzzz 5
b1111111111111000010000100001zzzz =
1_
0r
b1101 ?
0a
1t
b1110001z T
b11100111111101 O
b1110010z g
b11111110101110 b
b1110100z z
b1011100010001111 u
b1111000z /"
b111111100010111 *"
1!
#865000
0!
#870000
1!
#875000
0!
#880000
1!
#885000
0!
#890000
1"
1!
#895000
0!
#900000
0"
b111111111000010000100001zzzzzzzz 5
b111111111000010000100001zzzzzzzz =
1L
0_
b1110 ?
0N
1a
b110001zz T
b1110011111110 O
b110010zz g
b1001101111011111 b
b110100zz z
b101110001000111 u
b111000zz /"
b11111110001011 *"
1!
#905000
0!
#910000
1!
#915000
0!
#920000
1!
#925000
0!
#930000
1"
1!
#935000
0!
#940000
0"
b11111000010000100001zzzzzzzzzzzz 5
b11111000010000100001zzzzzzzzzzzz =
0L
b1111 ?
1N
b10001zzz T
b1000101001110111 O
b10010zzz g
b100110111101111 b
b10100zzz z
b10111000100011 u
b11000zzz /"
b1111111000101 *"
1!
#945000
0!
#950000
1!
#955000
0!
#960000
1!
#965000
0!
#970000
1"
1!
#975000
0!
#980000
0"
1r
1_
1L
0q
0^
0K
b1000 @
03
02
04
b1000 <
b1000010000100001zzzzzzzzzzzzzzzz 5
b1000010000100001zzzzzzzzzzzzzzzz =
1'"
b1000 :
b111 ?
0S
0f
0y
0)"
b1zzzz T
b100010100111011 O
b10zzzz g
b10011011110111 b
b100zzzz z
b1011100010001 u
b1000zzzz /"
b111111100010 *"
1!
#985000
0!
#990000
1!
#995000
0!
#1000000
1!
#1005000
0!
#1010000
1"
1!
#1015000
0!
#1020000
0"
0&"
1q
b100 @
12
01
b100 <
b10000100001zzzzzzzzzzzzzzzzzzzz 5
b10000100001zzzzzzzzzzzzzzzzzzzz =
1r
1'"
b100 :
b1011 ?
1y
0t
0."
1)"
b1zzzzz T
b1010011010010101 O
b10zzzzz g
b1001011101110011 b
b100zzzzz z
b1000111110000000 u
b0zzzzz /"
b1000001111111001 *"
1!
#1025000
0!
#1030000
1!
#1035000
0!
#1040000
1!
#1045000
0!
#1050000
1"
1!
#1055000
0!
#1060000
0"
0r
0_
0q
1^
b10 @
13
02
b10 <
b100001zzzzzzzzzzzzzzzzzzzzzzzz 5
b100001zzzzzzzzzzzzzzzzzzzzzzzz =
0L
0'"
b10 :
b10 ?
0N
1f
0y
0)"
b1zzzzzz T
b1101011101000010 O
b10zzzzzz g
b1100111110110001 b
b0zzzzzz z
b1100001111001000 u
b0zzzzzz /"
b1100010111110100 *"
1!
#1065000
0!
#1070000
1!
#1075000
0!
#1080000
1!
#1085000
0!
#1090000
1"
1!
#1095000
0!
#1100000
0"
0^
1K
b1 @
03
14
b1 <
b1zzzzzzzzzzzzzzzzzzzzzzzzzzzz 5
b1zzzzzzzzzzzzzzzzzzzzzzzzzzzz =
0L
0_
b1 :
b1 ?
1S
1N
0f
0a
b1zzzzzzz T
b110101110100001 O
b0zzzzzzz g
b110011111011000 b
b0zzzzzzz z
b110000111100100 u
b0zzzzzzz /"
b110001011111010 *"
1!
#1105000
0!
#1110000
1!
#1115000
0!
#1120000
1!
#1125000
0!
#1130000
1"
1!
#1135000
0!
#1140000
b11110001 P
b11110010 c
b11110100 v
b11111000 +"
0-"
0x
0e
0R
b0 9
1)
b11111111111111111000010000100001 (
b11111111111111111000010000100001 8
0/
00
0"
xr
x_
z&"
zq
z^
zK
bz @
z3
z2
z1
z4
bz <
bz 5
bz =
xL
x'"
bz :
b1000 ?
zS
0N
zf
zy
z."
1)"
bz T
b11010111010000 O
bz g
b11001111101100 b
bz z
b11000011110010 u
bz /"
b11000101111101 *"
1!
#1145000
0!
